{"absalom_bouncer":1,"absolute_loyalty":1,"accelerated_drinker":1,"aldori_caution":1,"ambush_training":1,"anatomist":1,"armed_grit":1,"armor_expert":1,"armored_rider":1,"armored_soul":1,"arodenite_sword_training":1,"axe_to_grind":1,"back_for_more":1,"battlefield_disciple":1,"berserker_of_the_society":1,"black_powder_bravado":1,"black_powder_fortune":1,"black_powder_interjection":1,"blackjacket_weapon_flair":1,"blade_of_the_society":1,"blights_bane":1,"bloodthirsty":1,"bloody_minded":1,"born_under_the_cradle":1,"born_under_the_dreamer":1,"born_under_the_stranger":1,"broken_not_beaten":1,"bullied":1,"careful_combatant":1,"clockwork_engineer":1,"coherent_rage":1,"cold_and_calculating":1,"courageous":1,"crimson_carapace":1,"crowd_dodger":1,"dedicated_defender":1,"defender_of_the_society":1,"deft_dodger":1,"demon_slayer":1,"demon_smiter":1,"devil_fighter":1,"dirty_fighter_apg":1,"dirty_trickster":1,"disillusioned":1,"dispelled_battler":1,"dormant_defense":1,"dragon_armor":1,"dueling_cloak_adept":1,"easy_way_or_the_hard_way":1,"elemental_apprentice":1,"evasive_sting":1,"excitable":1,"failed_aspirant":1,"faiths_hunter":1,"fencer":1,"firebug_qac":1,"fugitive":1,"guerrilla_tactics":1,"hard_to_kill":1,"hellknight_devotion":1,"hellknight_initiate":1,"helpful_cop":1,"hidden_hand":1,"hill_fighter":1,"holdout":1,"honored_fist_of_the_society":1,"hunters_knack":1,"ichimeiyo_champion":1,"improvised_defense":1,"indelible_ire":1,"inspiring":1,"inspiring_rush":1,"jacket_training":1,"jungle_fighter":1,"just_like_new":1,"killer":1,"kin_guardian":1,"larger_than_life":1,"lastwall_defender":1,"martial_performer":1,"merciful_scimitar":1,"monk_weapon_skill":1,"monster_challenger":1,"monster_survivor":1,"muscle_of_the_society":1,"natural_flyer":1,"natures_mimic":1,"never_stop_shooting":1,"no_escape":1,"obari_veteran":1,"ogre_avoidance":1,"ozem_inspired":1,"performers_surprise":1,"permanent_scars":1,"pillager":1,"promising":1,"punish_insurrection":1,"reactionary":1,"reckless":1,"reckless_contempt":1,"red_mantis_bleeding":1,"resilient":1,"resolve_of_the_rejected":1,"riders_bond":1,"river_fighter":1,"roving_range":1,"savanna_hunter":1,"scarred_by_space_pirates":1,"scarred_descendant":1,"shadow_trained":1,"siege_defender":1,"slippery":1,"soaring_sprinter":1,"solitary":1,"spirit_of_the_law":1,"splash_attack":1,"sprint":1,"startling_report":1,"steel_skin":1,"strong_arm_supple_wrist":1,"subjective_equilibrium":1,"surprise_weapon":1,"sworn_enemy":1,"tactician":1,"tar_taargadth_trained":1,"tarnished_halls_runner":1,"threatening_defender":1,"thunder_and_fang_performer":1,"to_the_last":1,"tracker_of_the_society":1,"unblemished_barrel":1,"undergrowth_specialist":1,"unpredictable_reactions":1,"vandal":1,"vengeful_combat":1,"venom_resistance":1,"vigilant_battler":1,"volatile_fuse":1,"wary_eye":1,"weapon_of_peace":1,"witty_repartee":1,"youthful_infiltrator":1,"abject_belief":1,"acclimatize_alignment":1,"acolyte_of_apocrypha":1,"apprentice":1,"arcane_scholar":1,"aspect_of_the_quah":1,"authoritarian":1,"beacon_of_faith":1,"birthmark":1,"blessed":1,"blessed_touch":1,"born_free":1,"bound_by_honor":1,"called":1,"canon_of_coin":1,"caretaker":1,"child_of_the_temple":1,"chosen_of_iomedae":1,"covert_channeler":1,"crisis_of_faith":1,"crusader":1,"darkest_before_dawn":1,"deep_faith":1,"defy_madness":1,"devoted_healer":1,"devotee_of_the_green":1,"devout_visionary":1,"disdainful_defender":1,"divine_confidante":1,"divine_denier":1,"dogged":1,"earthbound":1,"ease_of_faith":1,"eldritch_smith":1,"empyreal_pantheon":1,"exalted_of_the_society":1,"eye_for_the_wondrous":1,"faithful_feedback":1,"fates_favored":1,"fearless_defiance":1,"first_memories":1,"focused_disciple":1,"godclaw_disciple":1,"greater_adept_of_the_society":1,"havoc_of_the_society":1,"heedful_readiness":1,"hellknight_inquisitor":1,"heretics_caution":1,"hidden_faith":1,"history_of_heresy":1,"honest":1,"imperfect_recall":1,"indomitable_faith":1,"inhabitant_of_illusion":1,"inspired":1,"irrepressible":1,"irreverent":1,"jinx_eater":1,"kalistocratic_prophecy":1,"light_in_the_darkness":1,"loyalty_across_lifetimes":1,"lucid_dreamer":1,"martial_manuscript":1,"masked":1,"meditative_rest":1,"monastic":1,"mystery_initiate":1,"natural_ritualist":1,"naturally_gifted":1,"nature_worshiper":1,"necrotic_aura":1,"oathbound":1,"omen":1,"pact_servant":1,"patient_calm":1,"perpetual_companion":1,"persuasive_insight":1,"planar_savant":1,"priest_blessed":1,"principled":1,"prophesied":1,"proxy_of_many":1,"rebuke_the_curse":1,"redeemer":1,"reincarnated":1,"religious_reformer":1,"river_acumen":1,"sacred_conduit":1,"sacred_touch":1,"scholar_of_the_great_beyond":1,"schooled_inquisitor":1,"scourge_of_the_darkness":1,"second_tongue":1,"secret_keeper":1,"self_actualization":1,"self_sustaining":1,"soul_searchers_strength":1,"spell_intuition":1,"spirit_sense":1,"st_clydwells_ward":1,"stalwart_of_the_society":1,"strength_of_submission":1,"strength_of_the_land":1,"student_of_history":1,"tar_baphons_whisper":1,"tireless_avenger":1,"totemist":1,"traditionalist":1,"trickster_gnome":1,"two_world_magic":1,"undaunted":1,"unnatural_presence":1,"unshackled":1,"untrained_scholar":1,"urban_acolyte":1,"vile_domain":1,"wanderers_shroud":1,"wendifa_apprentice":1,"zealot":1,"zealots_bearing":1,"zealous_striker":1,"acrobat":1,"adopted":1,"affable":1,"allies_in_the_deep":1,"ambitious":1,"amiable_blunder":1,"amiable_briber":1,"ancestral_armor":1,"arodenite_historian":1,"artisan":1,"avid_reader":1,"balanced_determination":1,"bastard_uc":1,"beast_bond":1,"beastkin":1,"binders_blood":1,"brastlewark_businessman_gog":1,"bruising_intellect":1,"bully":1,"bureaucrats_favored":1,"calculated_bribe":1,"callous":1,"canter":1,"carnal_attraction":1,"charming":1,"chelish_sympathizer":1,"child_of_the_streets":1,"chip_on_the_shoulder":1,"civilized":1,"clever_wordplay":1,"collector":1,"competitive":1,"contagious_mettle":1,"contemptuous":1,"convincing_liar":1,"criminal":1,"criminal_roots":1,"criminally_connected":1,"cutting_condescension":1,"cynical":1,"cynical_ear":1,"darklands_scholar":1,"darklands_trader":1,"debauchery_defier":1,"deep_cover":1,"destined_diplomat":1,"detect_disobedience":1,"dismantle_order":1,"doublespeak":1,"draconic_destiny":1,"dragon_hunted":1,"dragon_pact":1,"drake_anatomist":1,"dusk_market_bribery":1,"ecumenical":1,"elemental_negotiator":1,"enemy_of_slavers":1,"escaped_captive":1,"etymologist":1,"excellent_penmanship":1,"explorer":1,"expressive_pantomime":1,"fast_talker":1,"feral_speech":1,"for_the_money":1,"founders_heritage":1,"free_spirit":1,"friend_in_every_town":1,"friends_in_high_places":1,"friends_in_low_places":1,"fury_of_the_red":1,"gesture_expertise":1,"gifted_smuggler":1,"gregarious":1,"grief_filled":1,"grim_optimism":1,"hardly_a_fool":1,"harvester":1,"heart_of_two_worlds":1,"hellknight_ancestry":1,"imposing_scion":1,"inexorable_authority":1,"infernal_colleague":1,"influence":1,"jistkan_scholar":1,"keleshite_princess":1,"king_in_waiting":1,"knowing_the_enemy":1,"law_enforcer":1,"life_of_toil":1,"lost_nobility":1,"maestro_of_the_society":1,"malevolent_temptations":1,"marked_by_unknown_forces":1,"master_messenger":1,"mediator":1,"memorable":1,"mentored":1,"mercenary":1,"merchant":1,"mock_gladiator":1,"monster_scholar":1,"monster_stalker":1,"natural_born_leader_social":1,"nightstalls_navigator":1,"noble_savage":1,"nonchalant_thuggery":1,"numerian_fluid_indulger":1,"obnoxious":1,"official_ties":1,"ordinary":1,"orphaned":1,"outsider_enemy":1,"pack_savvy":1,"passionate_inertia":1,"poverty_stricken":1,"practiced_disruptor":1,"preternatural_awareness":1,"questing_hellknight":1,"reassuring_advice":1,"red_silk_frankness":1,"relic_proof":1,"rest_for_the_wicked":1,"rich_parents":1,"rugged_dragon_hunter":1,"savage":1,"savant":1,"seafaring_reputation":1,"secret_keeper_qac":1,"seeker":1,"self_reliant":1,"signature_moves":1,"simple_disciple":1,"slave_runner":1,"snowbound":1,"student_of_philosophy":1,"style_sage":1,"subjective_truth":1,"supportive":1,"suspicious":1,"talented":1,"tireless_logic":1,"triaxus_trained":1,"tropical_upbringing":1,"trustworthy":1,"truths_agent":1,"unabashed_gall":1,"unbalanced_insight":1,"unintentional_linguist":1,"unnatural_revenge":1,"unpredictable":1,"untapped_potential":1,"unwelcome_business":1,"veiled_disciple":1,"vengeful_social":1,"vigilant_spycatcher":1,"voices_in_your_head":1,"wanderlust":1,"wasteland_vargrant":1,"weathered_emissary":1,"wicked_leader":1,"wiscrani_ear":1,"worldly":1,"acadamae_neophyte":2,"aeromantic_affinity":2,"air_touched":2,"alchemical_adept":2,"alchemical_intuition":2,"arcane_researcher":2,"arcane_revitalization":2,"arcane_temper":2,"ascendant_recollection":2,"balancers_banishing":2,"black_blood_heritage":2,"bladed_magic":2,"child_of_the_moon":2,"classically_schooled":2,"coven_casting":2,"cross_disciplined":2,"cross_knowledge":2,"fey_protection":2,"flame_touched":2,"focused_burn":2,"focused_mind":2,"fortunate":2,"gifted_adept":2,"greater_link":2,"greater_purpose":2,"green_blooded":2,"guiding_spirit":2,"hedge_magician":2,"hex_proof":2,"horrifying_mind":2,"house_of_green_mothers_pupil":2,"insistent_benefactor":2,"internal_compass":2,"inured_to_death":2,"keen_appraiser":2,"kin_bond":2,"knowledgeable_caster":2,"lamias_bane":2,"less_effort":2,"linked_surge":2,"low_blow":2,"lunar_birth":2,"magic_crafter":2,"magical_flair":2,"magical_knack":2,"magical_lineage":2,"magical_talent":2,"malleable_magic":2,"mathematical_prodigy":2,"mechanical_aptitude":2,"meticulous_concoction":2,"pragmatic_activator":2,"precise_treatment":2,"radiant_healing":2,"reluctant_apprentice":2,"resilient_caster":2,"rivethun_adherent":2,"scholar_of_the_analects":2,"scorned_by_magic":2,"secret_scrolls":2,"self_taught_scholar":2,"shrouded_casting":2,"skeptic":2,"spark_of_creation":2,"spiritual_attachment":2,"stabbing_spells":2,"storm_touched":2,"strength_foretold":2,"sun_blessed":2,"tenacious_shifting":2,"theoretical_magician":2,"dangerously_curious":2,"demonblight_reistance":2,"desperate_focus":2,"desperate_resolve":2,"desperate_speed":2,"diabolical_dabbler":2,"distance_aptitude":2,"domineering":2,"draconic_infusion":2,"earth_touched":2,"eldritch_auditor":2,"eldritch_delver":2,"elemental_accident":2,"enduring_mutagen":2,"outcasts_intuition":2,"outer_dragon_blood":2,"outsider_ties":2,"overwhelming_beauty":2,"partial_protege":2,"pathfinders_focus":2,"perfectionists_brew":2,"planar_escapee":2,"possessed":2,"mutant_eye":2,"transmuter_of_korada":2,"twinned_presence":2,"twisted_tattoo":2,"unscathed":2,"unseen_but_not_undone":2,"unstable_mutagen":2,"volatile_conduit":2,"water_touched":2,"winter_witchcraft_survivor":2,"beast_of_the_society":2,"bountiful_herb_lore":2,"charlatan":2,"deep_guardian":2,"chance_savior":2,"inspired_by_greatness":2,"making_good_on_promises":2,"on_the_payroll":2,"subject_of_study":2,"teachers_pet":2,"child_of_infamy":2,"conspiracy_hunter":2,"diabolist_raised":2,"infernal_bastard":2,"shadow_child":2,"the_pathfinders_exile":2,"westcrown_firebrand":2,"betrayed_cotct":2,"dockside_avenger":2,"drug_addict":2,"framed":2,"love_lost":2,"missing_child":2,"unhappy_childhood":2,"varisian_immunity":2,"artifact_hunter_gs":2,"dragonfoe":2,"dwarf_trained":2,"giant_blooded":2,"giantslayer_scion":2,"orphaned_by_giants":2,"roll_with_it":2,"student_of_giantkind":2,"trunau_native":2,"vexing_defender":2,"child_of_kintargo":2,"diva_in_training":2,"ex_asmodean":2,"fed_up_citizen":2,"gifted_satirist":2,"historian_of_the_rebellion":2,"natural_born_leader_hr":2,"pattern_seeker":2,"star_struck":2,"urban_sleuth":2,"amoral_mercenary":2,"apprentice_devilbinder":2,"asmodean_acolyte":2,"chelish_noble":2,"erratic_malefactor":2,"ex_iomedaean":2,"good_slip":2,"hellknight_aspirant":2,"local_tough":2,"scion_of_the_nine_circles":2,"thrune_informant":2,"thrune_loyal_agent":2,"against_the_technic_league":2,"local_ties":2,"numerian_archaeologist":2,"robot_slayer":2,"skymetal_smith":2,"stargazer_ig":2,"animal_whisperer":2,"blight_burned":2,"chernasardo_hopeful":2,"foxclaw_scout":2,"frontier_healer":2,"ironfang_survivor":2,"kraggodan_castaway":2,"unbreakable_survivor":2,"world_weary":2,"best_customer":2,"best_friend":2,"caravan_guard":2,"childhood_crush":2,"foreign_tongued":2,"foster_child":2,"friend_of_the_family":2,"hero_worship":2,"rescued":2,"student_survivalist":2,"younger_sibling":2,"bastard_km":2,"brigand":2,"issian":2,"noble_born":2,"pioneer":2,"rostlander":2,"sword_scion":2,"earning_your_freedom":2,"finding_haleen":2,"gnoll_killer":2,"missionary":2,"reclaiming_your_roots":2,"seeking_adventure":2,"blood_of_pharaohs":2,"devotee_of_the_old_gods":2,"foreign_opportunist":2,"inquisitive_archaeologist":2,"mummy_cursed":2,"resurrected":2,"sphinx_riddler":2,"trap_finder":2,"undead_crusader":2,"wati_native":2,"adaptive_magic":2,"blood_of_giants":2,"failed_winter_witch_apprentice":2,"northern_ancestry":2,"restless_wayfarer":2,"vigilante_witch_hunter":2,"warded_against_witchery":2,"accidental_clone":2,"audrahnis_ally":2,"close_allies":2,"intrigued_by_thassilon":2,"scion_of_legend":2,"spirit_touched":2,"time_lost":2,"eager_performer":2,"family_ties_rotrl":2,"friends_and_enemies":2,"giant_slayer":2,"goblin_watcher":2,"hagfish_hopeful":2,"merchant_family":2,"monster_hunter":2,"sandpoint_faithful":2,"scholar_of_the_ancients":2,"student_of_faith":2,"thrill_seeker_rotr":2,"athletic":2,"azlanti_scholar_roapg":2,"eagle_knight_recruit":2,"employee":2,"expert_explorer":2,"following_in_the_footsteps":2,"healthy":2,"pathfinder_recruit":2,"resourceful":2,"seasoned_hunter":2,"set_mind":2,"skillful":2,"daring_doomsayer":2,"fixer_of_odds":2,"fools_for_friends":2,"into_enemy_territory":2,"looking_for_work":2,"optimistic_gambler":2,"portentous_perception":2,"researching_the_blot":2,"scouting_for_fiends":2,"boarded_in_cheliax":2,"boarded_in_mediogalti":2,"boarded_in_mwangi_expanse":2,"boarded_in_varisia":2,"boarded_in_the_shackles":2,"colonial":2,"get_the_cargo_through":2,"jenivere_crew":2,"mwangi_scholar":2,"stowaway":2,"alabaster_outcast":2,"ex_sczarni":2,"exchange_agent":2,"monument_scholar":2,"nontraditional_native":2,"ruin_raider":2,"serpent_runner":2,"ancient_explorer":3,"barroom_talespinner":3,"besmaras_blessing":3,"buccaneers_blood":3,"dockside_brawler":3,"eye_for_plunder":3,"ilizmagorti_native":3,"peg_leg":3,"ships_surgeon":3,"touched_by_the_sea":3,"driven_by_guilt":3,"enduring_stoicism":3,"foe_of_the_strange":3,"formerly_mind_swapped":3,"methodical_mind":3,"pugnacious":3,"ritualistic":3,"sensitive_mind":3,"true_devotion":3,"twitchy":3,"the_artisan":3,"the_lawbringer":3,"the_optimist":3,"the_outsider":3,"the_pessimist":3,"the_reclaimer":3,"the_snoop":3,"the_word":3,"athletic_champion":3,"child_of_oppara":3,"disgraced_noble":3,"rising_star":3,"senatorial_hopeful":3,"taldan_patriot":3,"young_reformer":3,"chance_encounter":3,"child_of_the_crusades_wotr":3,"exposed_to_awfulness":3,"riftwarden_orphan":3,"stolen_fury":3,"touched_by_divinity":3,"black_sheep":3,"favored_son_or_daughter":3,"outlander":3,"augmented_disguise":3,"dealmaker":3,"extremely_fashionable":3,"heirloom_weapon":3,"improvisational_equipment":3,"iron_liver":3,"power_of_suggestion":3,"prehensile_whip":3,"quick_learner":3,"rough_and_ready":3,"stage_magic":3,"stealthy_escape":3,"thrown_together_fashion":3,"well_provisioned_adventurer":3,"betrayal_of_trust":3,"blood_resonance":3,"family_resemblance":3,"family_trade":3,"honor_bound":3,"rivalry":3,"tight_bonds":3,"black_as_night":3,"burst_of_speed":3,"clever_mount":3,"cunning_breed":3,"fleet_of_foot":3,"keleshite_trade_camel":3,"lucky_hound":3,"mindspin_mountain_goat":3,"relentless_fortitude":3,"stalwart_elk":3,"warthog":3,"water_trained":3,"weather_beaten":3,"a_shining_beacon":3,"accident_resistant":3,"adherent_of_ancient_osirion":3,"adventurous_imbiber":3,"affinity_for_the_elements":3,"agent_of_chance":3,"alluring":3,"always_threatening":3,"ambassador":3,"ancestors_blade":3,"andolettas_consolation":3,"angradds_flame":3,"angradds_valor":3,"arcane_depth":3,"avowed_inspiration":3,"backstabber":3,"battlefield_caster":3,"battlefield_surgeon":3,"besmaras_name":3,"besmaras_strength":3,"bestial_wrath":3,"blade_of_mercy":3,"blessed_orphan":3,"blessing_of_the_feast":3,"blind_zeal":3,"bloody_vengeance":3,"brighs_insight":3,"broken_mind":3,"calistrian_courtesan":3,"call_for_help":3,"centered":3,"chaldiras_luck":3,"cheat_death":3,"child_of_nature":3,"cleansing_light":3,"cleansing_the_twisted":3,"clockwork_surgeon":3,"contract_master":3,"corpse_cannibal":3,"corpse_hunter":3,"covenant_of_abaddon":3,"dawn_renewal":3,"deadeye_bowman":3,"deathspeaker":3,"deck_fighter":3,"deep_wounding":3,"defensive_strategist":3,"deformed":3,"demon_hunter":3,"demonic_persuasion":3,"demoralizing_presence":3,"denial_of_fate":3,"destructive_blows":3,"devotee_of_a_dead_god":3,"diseased_heart":3,"divine_warrior":3,"dragon_tracker":3,"dragonslayer":3,"ear_for_music":3,"elemental_resilience":3,"elven_polytheist":3,"empty_heart_full_heart":3,"empyreal_focus":3,"enchanting_conniver":3,"enemy_of_delusion":3,"envoy_of_healing":3,"erastils_speaker":3,"eternal_understanding":3,"expert_boarder":3,"extended_toil":3,"eye_for_quality":3,"eye_of_arqueros":3,"eye_of_the_father":3,"eyes_and_ears_of_the_city":3,"eyes_of_the_wild":3,"faithful_arodenite":3,"faithful_artist":3,"fatal_trapper":3,"favored_prey":3,"fiendish_confidence":3,"flame_of_the_dawnflower":3,"flames_of_hell":3,"flounderer":3,"folgrits_bounty":3,"folgrits_mercy":3,"follower_of_the_stars":3,"fortified_drinker":3,"frightening_speed":3,"fruits_of_your_labor":3,"furious_vengeance":3,"fury":3,"gemstone_collector":3,"gifted_medium":3,"good_dreams":3,"good_natured":3,"gozrehs_sight":3,"guardian_smite":3,"guardian_of_the_forge":3,"hatred_of_the_gods":3,"holy_schemer":3,"honey_tongued":3,"honeyed_words":3,"illuminator":3,"inheritors_immunity":3,"inner_beauty":3,"inoculated":3,"inspiring_leader":3,"intense_artist":3,"iron_grip":3,"know_the_land":3,"kuthite_caster":3,"lessons_of_chaldira":3,"liars_tongue":3,"light_sleeper":3,"light_bringer":3,"living_bulwark":3,"loreseeker":3,"lover_of_the_law":3,"loyal_bond":3,"magic_is_life":3,"magics_might":3,"mighty_protector":3,"mischievous_smile":3,"mothers_rage":3,"mothers_teeth":3,"natural_magic":3,"natural_philosopher":3,"nimble_fingers_keen_mind":3,"oathkeepers_vow":3,"opener_of_doors":3,"opportune_slayer":3,"opportunistic":3,"pain_is_pleasure":3,"patient_optimist":3,"planar_wayfarer":3,"poisonous_slayer":3,"potent_concoctions":3,"practiced_deception":3,"pristine_reputation":3,"propitiation":3,"protective_faith":3,"provider":3,"purity_of_faith":3,"reckless_luck":3,"redeemed_by_ragathiel":3,"regal_presence":3,"rejected_emperor":3,"relentless_duty":3,"resigned":3,"resilient_martyr":3,"restless_hunger":3,"river_freedom":3,"rousing_courage":3,"sacred_avenger":3,"sacred_orienteer":3,"sacred_smasher":3,"scaly_ally":3,"scarred_by_war":3,"searing_beacon":3,"secret_knowledge":3,"seer_of_reality":3,"self_sacrifice":3,"sense_of_order":3,"sensing_imperfection":3,"serpentine_squeeze":3,"shadow_whispers":3,"shaper_of_reality":3,"shared_ancestors":3,"shield_trained":3,"sovyrian_pantheist":3,"spirit_guide":3,"spirit_talker":3,"split_second_defense":3,"stabilizing_touch":3,"starchild":3,"starlit_hexer":3,"steady_strength":3,"stoic_optimism":3,"strength_of_the_barghest":3,"strength_of_the_sun":3,"strengths_fanfare":3,"strict_judgment":3,"strip_the_veils":3,"strong_heart":3,"strong_swimmer":3,"strong_willed":3,"structural_knowledge":3,"talented_organizer":3,"the_city_protects":3,"the_flexing_arm":3,"thirst_for_knowledge":3,"thrill_seeker_isg":3,"toilcrafter":3,"twisted_transformations":3,"undead_slayer_pharasma":3,"under_siege":3,"underlying_principles":3,"unhinged_mentality":3,"unspeakable_bond":3,"unswaying_love":3,"veils_upon_veils":3,"venom_drenched":3,"veteran_of_battle":3,"vindictive_strike":3,"voice_of_monsters":3,"wasp_whisperer":3,"wedded_bliss":3,"well_prepared":3,"wisdom_in_the_flesh":3,"wise_teacher":3,"wolf_cub":3,"worthless_pawn":3,"wrecking_wrath":3,"wronged":3,"anxious":3,"arcane_malignancies":3,"attached":3,"avarice":3,"betrayed_drawback":3,"bitter":3,"burned":3,"condescending":3,"cowardly":3,"cruelty":3,"dependent":3,"doubt":3,"empty_mask":3,"entomophobe":3,"envy":3,"family_ties_drawback":3,"fey_taken":3,"forgetful":3,"foul_brand":3,"guilty_fraud":3,"haunted":3,"haunting_regret":3,"headstrong":3,"hedonistic":3,"helpless":3,"impatient":3,"infamous":3,"information_overload":3,"insatiable":3,"lonely":3,"loner":3,"lovesick":3,"magical_klutz":3,"mark_of_slavery":3,"meticulous":3,"misbegotten":3,"naive":3,"nervous":3,"oblivious":3,"occult_bargain":3,"oppressive_expectations":3,"overprotective":3,"paranoid":3,"power_hungry":3,"pride":3,"provincial":3,"righteous_indignation":3,"scarred":3,"secret_shame":3,"self_doubting":3,"sentimental":3,"shadow_scarred":3,"sheltered":3,"sleepy":3,"spooked":3,"stigmatized":3,"superstitious_drawback":3,"tainted_spirit":3,"too_many_secrets":3,"umbral_unmasking":3,"unlearned":3,"vain":3,"vainglory":3,"warded_against_nature":3,"xenophobic":3,"zealous_drawback":3,"the_thrush":3,"the_lantern_bearer":3,"the_newlyweds":3,"the_bridge":3,"the_daughter":3,"the_rider":3,"the_patriarch":3,"the_wagon":3,"the_pack":3,"the_mother":3,"the_star_gazer":3,"the_stranger":3,"the_follower":3,"aballonian_resilience":4,"abendego_pilot":4,"abendego_spellpiercer":4,"aberration_hunter":4,"abolitionist_hunter":4,"absalom_hotspur":4,"abyssal_eavesdropper":4,"accustomed_to_trickery":4,"acolyte_of_razmir":4,"acupuncturist":4,"agent_of_the_sultana":4,"airship_captain":4,"akitonian_ferocity":4,"alabaster_odalisque":4,"alchemical_fence":4,"alchemical_prodigy":4,"alien_origins":4,"alkenstar_defender":4,"alkenstar_engineer":4,"altruistic_diplomat":4,"analytical":4,"ancestral_weapon":4,"andoren_freedom_fighter":4,"animal_spirit_vitality":4,"antiquities_smuggler":4,"anuli_engineer":4,"aquatic_survivalist":4,"armun_kelisk_scholar":4,"artifact_hunter_isp":4,"ash_bane":4,"aspiring_hellknight":4,"awakened_from_stasis":4,"azlanti_scholar_hftf":4,"balanced_education":4,"bandit":4,"beachcomber":4,"belem_pirate":4,"bellflower_tiller":4,"bellis_axe_master":4,"bellis_honey_harvester":4,"bellis_log_roller":4,"betrayed_ex_noble":4,"big_game_hunter":4,"black_eagle_recruit":4,"blackthorn_rancher":4,"blessed_of_the_norns":4,"blighted_physiology":4,"blood_potion_brewer":4,"blooded":4,"border_guard":4,"born_under_the_green_star":4,"bounty_hunter":4,"brave_words":4,"brevoy_bandit":4,"briar_bandit":4,"call_of_the_longships":4,"candidate_for_perfection":4,"caravan_nomad":4,"carpenden_lobber":4,"carpenden_roof_runner":4,"cavern_survivor":4,"centaur_vengeance":4,"chainbreaker":4,"channel_the_earth":4,"charau_ka_slayer":4,"charmed_innocent":4,"cheap_to_feed":4,"chelish_guerrilla":4,"child_of_mumia":4,"child_of_wati":4,"child_of_the_crusades_isp":4,"chillblight_emissary":4,"chilled_by_brutality":4,"chivalrous":4,"chosen_child":4,"citizen_of_eleder":4,"citizen_of_kalabuto":4,"clan_artisan":4,"cliff_jumper":4,"cliff_strider":4,"cliff_master":4,"cloistered_upbringing":4,"clumsy_slave":4,"coin_hoarder":4,"coincunning":4,"cold_heart":4,"commercial_savvy":4,"community_minded":4,"confidante_to_the_oppressed":4,"conscientious_miner":4,"corpse_dodger":4,"cosmopolitan":4,"cruel_master":4,"crusader_road_acolyte":4,"crusader_tactician":4,"cultist_lineage":4,"cultivated":4,"cunning_liar":4,"curse_queller":4,"cynic":4,"cypher_resistance":4,"cyphermage_backer":4,"darkblight_survivor":4,"darklands_delver":4,"debt_to_a_witch":4,"demon_eradicator":4,"demon_proof_mind":4,"demonbane_summoner":4,"desert_child":4,"destined_for_greatness":4,"devilfish_diver":4,"devotee_of_kalistrade":4,"diligence":4,"dinosaur_whisperer":4,"discerning_beliefs":4,"div_hunter":4,"divine_deceiver":4,"dominator":4,"draconic_vigil":4,"dreadful_forethought":4,"dtang_ma_bloodline":4,"dump_salvager":4,"dungeon_dweller":4,"dusk_dancer":4,"duskwalker_agent":4,"eager_combatant":4,"educated_druggist":4,"egorian_school_apprentice":4,"elemental_endowment":4,"elemental_pupil":4,"elemental_ties":4,"elven_bitterness":4,"emberkin_imposter":4,"emissary":4,"empathic_diplomat":4,"empyreal_cultist":4,"enchanted_by_giants":4,"enemy_of_the_undead":4,"eoxian_experiment":4,"equality_for_all":4,"erutaki_sky_reader":4,"evident_supporter":4,"exhibition_fighter":4,"exiled_scholar":4,"expert_smuggler":4,"expert_swimmer":4,"eye_of_the_falcon":4,"fangwood_diplomat":4,"fangwood_insurgent":4,"fey_hex":4,"fey_mediator":4,"fey_wise":4,"fiery_dominance":4,"fight_for_liberty":4,"flotsam":4,"footsteps_of_aganhei":4,"forbidden_knowledge":4,"fortune_found":4,"free_agent":4,"free_people":4,"freed_slave_andoran":4,"freed_slave_katapesh":4,"freedom_fighter_andoran":4,"freedom_fighter_shokuro":4,"friend_of_the_dead":4,"friend_of_the_fey":4,"frontier_forged":4,"frostborn":4,"fruit_merchant":4,"gallant_imposter":4,"genie_caller":4,"ghost_survivor":4,"ghoulish_affinity":4,"giant_ambivalence":4,"giant_dodger":4,"giant_investigator":4,"giant_harried":4,"glory_of_old":4,"goblin_pirate":4,"godless_resolve":4,"gold_goblin_regular":4,"good_folk":4,"gravelwalker":4,"greenskin_stalker":4,"grit_goggles":4,"guerilla":4,"guerrilla_mender":4,"heart_of_clay":4,"heavenly_touch":4,"heir_of_chu_ye":4,"hermean_paragon":4,"highlander":4,"holy_tattoo":4,"home_port":4,"honeyed_tongue":4,"hongal_bloodrider":4,"huldras_luck":4,"humble_beginnings":4,"hurricane_savvy":4,"hwan_artist":4,"iadaran_illusionist":4,"imperial_soldier":4,"indentured_blacksmith":4,"inspiring_speaker":4,"instigator_of_rebellion":4,"intrepid_delver":4,"iobarian_survivor":4,"iron_lungs":4,"iron_mind":4,"isger_fixer":4,"isgeri_orphan":4,"issian_noble":4,"jadwiga_medicine":4,"jungle_diplomat":4,"jungle_guide":4,"jungle_native":4,"jungle_resilience":4,"jungle_walker":4,"justiciar":4,"kami_talker":4,"keeper_of_the_veil":4,"keleshite_trader":4,"kobolds_neighbor":4,"kwanlai_believer":4,"kyonin_gatekeeper":4,"lair_snake":4,"lamasaran_performer":4,"lastwall_cavalry_rider":4,"left_behind":4,"legalistic_liberation":4,"lepidstadt_scar":4,"lichblood":4,"linebreaker":4,"lingshens_finest":4,"lions_audacity":4,"liquid_healing":4,"local_know_it_all":4,"log_roller":4,"lost_origins":4,"lost_role_model":4,"mammoth_master":4,"mana_wastes_medic":4,"mana_wastes_survivalist":4,"master_of_peaks":4,"mechanical_expertise":4,"merabian_mentorship":4,"merchant_of_katheer":4,"merchants_child":4,"militia":4,"militia_veteran":4,"minkai_advocate":4,"mivoni_duelist":4,"mizu_ki_hikari_rebel":4,"monkey_goblin":4,"mordant_heritage":4,"mountain_guide":4,"mutabi_qi_explorer":4,"mwangi_herbal_tradition":4,"mwangi_linguist":4,"naga_emissary":4,"narrow_escape":4,"narrows_survivor":4,"naturalist":4,"near_death_experience":4,"necrotoxin_resistance":4,"nexian_corpse_hunter":4,"nidalese_shadowcaster":4,"nightstall_urchin":4,"nightstalls_escapee":4,"nirmathi_militia":4,"noble_in_exile":4,"numerologist":4,"oagan_diver":4,"obsequious_morsel":4,"observant_archer":4,"oenopion_alchemist":4,"offspring_of_the_ascension":4,"open_minded_explorer":4,"orc_impaler":4,"oregent_desperation":4,"oregent_timing":4,"oregent_vandal":4,"osirionologist":4,"outsea_native":4,"palm_potion":4,"paraheen_weaponsmith":4,"passionate_believer":4,"patrons_boon":4,"pearl_diver_xidao":4,"perseverance":4,"pesh_addict":4,"pesh_dealer":4,"pirate_duelist":4,"pitaxian_improvisation":4,"plainsman":4,"planar_negotiator_dhh":4,"poison_connoisseur":4,"poisoned_blade_resistance":4,"pomp_and_pageantry":4,"precocious_spellcaster":4,"prestigious_healer":4,"pretend_pirate":4,"prismati_player":4,"privileged_slave":4,"prophet_of_burrows":4,"purchased_loyalty":4,"pure_legion_recruit":4,"quain_martial_artist":4,"quantium_university_graduate":4,"rabble_rebel":4,"rahadoumi_cultist":4,"rahadoumi_disbeliever":4,"rebel_leader":4,"regional_influence":4,"regional_recluse":4,"resourceful_alchemy":4,"resourceful_scavenger":4,"rice_runner":4,"rider_of_paresh":4,"river_navigator":4,"river_rat":4,"river_sniper":4,"riverfolk":4,"roof_racer":4,"runaway_slave":4,"sargavan_guard":4,"savage_breaker":4,"savanna_child":4,"scion_of_goblinblood":4,"scion_of_the_shory":4,"scourge_of_the_seas":4,"scrambling_servant":4,"screaming_leap":4,"sea_souled":4,"seasoned_climber":4,"secret_revolutionary":4,"secret_of_the_impossible_kingdom":4,"servitor_of_spirits":4,"sevenarches_seeker":4,"shackles_seafarer":4,"shadow_dealer":4,"shadow_dissident":4,"shadow_shaman":4,"shadowsight":4,"shaer":4,"sharp_eyes":4,"shenmen_prospector":4,"ship_aptitude":4,"shipboard_caster":4,"shoanti_tribesman":4,"signaler":4,"silent_watcher":4,"silvertongued_eunuch":4,"skilled_surgeon":4,"sky_spirit_worshipper":4,"skymetal_affinity":4,"slave_taker":4,"slayer_of_the_deep":4,"snake_bleeder":4,"snake_handler":4,"snowstride":4,"social_slaver":4,"sodden_chld":4,"soldier_of_the_faith":4,"solidarity":4,"sophisticated_citizen":4,"sound_of_mind":4,"spell_duel_prodigy":4,"spirit_animal":4,"spiritual_forester":4,"star_reader":4,"stargazer_region":4,"storm_hunter":4,"stormrunner":4,"stream_nomad":4,"street_wary":4,"suck_in_your_gut":4,"sun_orchid_harvester":4,"sun_blasted":4,"superstitious_isp":4,"superstitious_ward":4,"surefooted_ascent":4,"surface_stranger":4,"sustaining_performance":4,"swamp_rebel":4,"swamp_recluse":4,"swamp_skulker":4,"swamp_survivor":4,"swordlords_page":4,"szaezan_crags_miner":4,"tanglebriar_guerrilla":4,"technic_tinkerer":4,"technological_brewmaster":4,"the_vessel_between":4,"thoughtful_wish_maker":4,"thuvian_merchant":4,"tianjing_temple_guard":4,"tiger_brigadier":4,"touched_by_the_sky":4,"town_gossip":4,"trap_savvy":4,"treasure_mapper":4,"treerazers_bane":4,"trench_navigator":4,"triaxian_tradition":4,"true_name_caller":4,"tundra_child":4,"unafraid":4,"underbridge_dweller":4,"undermarket_smuggler":4,"unflinching_faith":4,"unstuck":4,"uskwood_hunter":4,"ustalavic_noble":4,"uwaga_highlander":4,"vagabond_child":4,"valashmai_veteran":4,"valknar_alumnus":4,"varisian_wanderer":4,"venicaan_medic":4,"vialesk_historian":4,"viking_blood":4,"voices_of_solid_things":4,"void_child":4,"walking_ward":4,"wardbreaker":4,"warrior_poet":4,"wary_potr":4,"watching_taldor":4,"water_brave":4,"wayang_spellhunter":4,"wealthy_dabbler":4,"weed_resistance":4,"well_bred":4,"wharf_rat":4,"whip_specialist":4,"whisper_woods_hunter":4,"whitethrone_gourmand":4,"whole_hearted":4,"wild_wanderer":4,"windspeaker":4,"winners_luck":4,"winter_warrior":4,"winters_soul":4,"witch_tongued":4,"xa_hoi_soldier":4,"adrift":5,"celestial_community":5,"celestial_contact":5,"clergy_member":5,"ethical_leader":5,"faith_healer":5,"idealized_campaigner":5,"innocent":5,"martyrs_blood":5,"planar_negotiator_boa":5,"selective_health":5,"wary_boa":5,"celestial_tracker":5,"planetars_visions":5,"burnished_skin":5,"pyromancer":5,"enlightened_warrior":5,"speech_of_the_wilds":5,"good_influence":5,"lantern_spirit":5,"bralanis_step":5,"lillends_harp":5,"snake_hater":5,"toxophilite":5,"blood_algorithm":5,"cellular_match":5,"experimental_escapee":5,"nanite_revival":5,"deathtouched":5,"fiend_blood":5,"canopy_prowler":5,"inquisitive_banterer":5,"jungle_opportunist":5,"bitter_heart":5,"creative_manipulator":5,"creepy":5,"cruel_child":5,"magic_in_the_blood":5,"switched_at_birth":5,"acknowledged_scion":5,"born_in_the_light":5,"final_embrace":5,"undead_slayer_bog":5,"half_forgotten_secrets":5,"unidentifiable_appeal":5,"old_before_your_time":5,"thrall_spotter":5,"linguistic_genius":5,"numerological_gift":5,"mind_trapper":5,"sensual_graces":5,"arcane_prodigy":5,"fleshwarp_exposure":5,"poisonous_upbringing":5,"scheming_survivor":5,"vermin_driver":5,"ancestral_grounds":5,"brewmaster":5,"child_of_zolurket":5,"clearheaded":5,"deep_marker":5,"fungal_brewing":5,"goldsniffer":5,"grounded":5,"gunworker":5,"insular_dwarf":5,"militant_merchant":5,"ruthless":5,"sky_quester":5,"spellcasters_anathema":5,"tunnel_fighter":5,"warsmith":5,"zest_for_battle":5,"deathkeeper":5,"sphinxfriend":5,"arcane_dabbler":5,"dilettante_artist":5,"forlorn":5,"insular_elf":5,"keeper_of_the_secret_shame":5,"lapsed_faith":5,"planetary_traveler":5,"seeker_of_brightness":5,"sovyrian_intellectual":5,"tropical_botanist":5,"warrior_of_old":5,"wild_stride":5,"youthful_mischief":5,"obscure_traditions":5,"snowblooded":5,"adaptable_flatterer":5,"murky_allegiance":5,"shadow_stalker":5,"weathered":5,"creative_reality":5,"frustrating":5,"genie_heir":5,"minor_wishcraft":5,"honored_provider":5,"azlanti_inheritor":5,"memory_mastery":5,"adrenaline_rush":5,"animal_friend":5,"brastlewark_businessman_ceod":5,"efficient_packer":5,"forest_senses":5,"illusion_obsession":5,"industrious":5,"prankster":5,"rapscallion":5,"snowstepper":5,"vermin_wrangler":5,"advantageous_distraction":5,"balloon_headed":5,"big_ears":5,"bouncy":5,"bully_burner":5,"color_thief":5,"dog_sniff_hate":5,"foul_belch":5,"goblin_bravery":5,"pustular":5,"rude_songs":5,"ugly_swine":5,"canopy_shooter":5,"bifurcated_magic":5,"elven_reflexes":5,"experimental_rebel":5,"failed_apprentice":5,"pearl_diver_pots":5,"wild_domesticator":5,"child_of_two_peoples":5,"elven_serenity":5,"trade_talk":5,"almost_human":5,"brute_apg":5,"caravan_drover":5,"cruel_rager":5,"irritable_diplomat":5,"lasting_ferociousness":5,"legacy_of_sand":5,"mistrusted":5,"outcast":5,"promising_peacemaker":5,"scrapper":5,"wild_ferocity":5,"amazingly_ugly":5,"beast_rider":5,"big_mouth":5,"brute_orc":5,"deadeye":5,"demented_inventor":5,"dirty_fighter_orc":5,"mindlessly_cruel":5,"rage_of_storms":5,"tribal":5,"tusked":5,"unbreakable_hate":5,"iron_control":5,"finish_the_fight":5,"bellflower_contact":5,"freed_slave_fg":5,"freedom_fighter_halfling":5,"helpful_halfling":5,"intrepid_volunteer":5,"lettered":5,"perfect_servant":5,"providential_passenger":5,"scrounger":5,"slave_smuggler":5,"successful_shirker":5,"well_informed":5,"wild_shadow":5,"adventurous_explorer":5,"inciter_hobgoblin":5,"friend_to_animals":5,"plague_survivor":5,"scholar_of_ruins":5,"survivalist":5,"trifler":5,"world_traveler":5,"azlant_fanatic":5,"azlanti_engineering":5,"enduring_spellcraft":5,"nomadic":5,"bekyar_slave_maestro":5,"shoanti_spirit_singer":5,"glib_barrister":5,"infernal_influence":5,"ingratiating":5,"masterful_demeanor":5,"obsessed_with_success":5,"operatic":5,"colonial_entitlement":5,"spirit_lodge_dreamer":5,"effortless_aid":5,"ever_home":5,"eyes_of_the_sun":5,"historian":5,"relic_hunter":5,"tongue_of_many_towns":5,"zealous_garundi":5,"born_to_the_water":5,"jadwiga_scion":5,"carefully_hidden":5,"commanding":5,"genie_blood":5,"horse_lord":5,"market_rat":5,"pride_of_the_diamond_empire":5,"tempestuous_combatant":5,"thoroughbred":5,"divine_the_mystery":5,"ice_walker":5,"pragmatic_polytheist":5,"storied_scars":5,"superstitious_kellid":5,"wary_of_danger":5,"wasteland_hunter":5,"weathered_patience":5,"witness_to_natures_cruelty":5,"assimilated_native":5,"colonial_sympathizer":5,"magaambyan_arcana":5,"proud_tribesman":5,"river_trader":5,"spirits_in_the_stone":5,"student_of_nantambu":5,"trailblazer":5,"slaver":5,"auspicious_tattoo":5,"bred_for_war":5,"favored_champion":5,"oral_historian":5,"shoanti_steed":5,"shoanti_tattoo":5,"artistic_dilettante":5,"aspiring_bard":5,"blade_bravado":5,"destined_pioneer":5,"generous":5,"my_word_is_my_bond":5,"bureaucracy_navigator":5,"keeper_of_the_ancestral_scrolls":5,"master_of_the_sudden_strike":5,"nearly_blinded":5,"animalistic_affliction":5,"glint_tongued":5,"gruff_watcher":5,"honor_driven":5,"shield_bearer":5,"weapon_training":5,"harrow_born":5,"harrow_chosen":5,"practiced_gambler":5,"stargazer_human":5,"tattooed_focus":5,"varisian_tattoo":5,"varki_landspeaker":5,"disciplined_body":5,"latent_psion":5,"open_palm_of_irori":5,"sharp_wits":5,"voice_of_velvet":5,"expert_distractor":5,"fiery_glare":5,"hot_headed":5,"snap_ignition":5,"unflappable_arrogance":5,"adroit":5,"covered_sniper":5,"spidery_climber":5,"among_humans":5,"kami_respect":5,"nine_tailed_scion":5,"carnation_scales":5,"golden_scales":5,"kobold_faith":5,"purple_scales":5,"tribal_guide":5,"vexed":5,"bog_scamp":5,"ooze_defense":5,"sneaky_swimmer":5,"draconic_echo":5,"elaborate_trapper":5,"lightning_blessed":5,"liquid_tongued":5,"alchemical_breath":5,"kobold_herbalist":5,"slithering_stride":5,"fire_tongued":5,"firebug_kobold":5,"heat_fortitude":5,"smoke_resistant":5,"cold_fortitude":5,"frost_spitter":5,"icy_mementos":5,"skaters_balance":5,"castrovel_gatekeeper":5,"skilled_telepath":5,"tactile_telekinesis":5,"guarded":5,"longlung":5,"nagaji_nationalist":5,"animal_rustler":5,"brimstone_seer":5,"earthsense":5,"loner_of_the_rocks":5,"sandy_ambush":5,"statuesque":5,"stoic_dignity":5,"bauble_fascination":5,"business_venturer":5,"ratfolk_avenger":5,"scamper":5,"walls_of_half_truths":5,"curse_in_the_blood":5,"marked_by_natures_magic":5,"mastery_of_form":5,"traumatic_shift":5,"fight_with_the_flock":5,"precision_hearing":5,"durable_change":5,"reviving_rest":5,"boar_resilience":5,"strength_of_body":5,"crocodile_swim":5,"terrifying_lunge":5,"inured_to_disease":5,"rat_squeeze":5,"sharkchild":5,"shoreline_skirmisher":5,"feline_instinct":5,"tigers_claw":5,"lycanthropic_bloodlust":5,"shared_curse":5,"aerial_harrier":5,"dowsing":5,"dualborn":5,"elemental_caller":5,"instant_friendship":5,"practiced_impression":5,"secret_keeper_svirfneblin":5,"aerial_observer":5,"carrying_voice":5,"following_breeze":5,"thunderborn":5,"wind_carried_voices":5,"winged_aloofness":5,"seafaring_slayer":5,"anticipate_evil":5,"beast_bully":5,"blessing_of_darkness":5,"born_damned":5,"dark_magic_affinity":5,"enduring_heritage":5,"ever_wary":5,"family_connections":5,"fiendish_sniper":5,"friendless":5,"hard_to_pin_down":5,"inciter_tiefling":5,"malign_instrument":5,"motherless":5,"neutralizing_gut":5,"persecuted_expatriate":5,"prideful_temper":5,"prolong_magic":5,"shadow_stabber":5,"suicidal":5,"tempters_tongue":5,"twilight_zeal":5,"underling":5,"bent_body":5,"tough_skin":5,"arms_master":5,"prayer_breaker":5,"god_scorn":5,"repulsive":5,"deaths_deputy":5,"soul_eater":5,"blood_stalker":5,"unearth_secrets":5,"big_boned":5,"superior_clutch":5,"deadly_rush":5,"flair_for_destruction":5,"chain_master":5,"pain_artist":5,"buried_anxiety":5,"shift_the_blame":5,"repel_sin":5,"vile_kiss":5,"dragon_friend":5,"transitional":5,"triaxian_dragonslayer":5,"magic_survivor":5,"marids_fury":5,"slippery_step":5,"undine_loyalty":5,"water_shaping":5,"whiteout":5,"calculated_risk":5,"in_tune_with_language":5,"proud_progenitor":5,"weatherworn":5,"rapid_drain":5,"telekinetic_dependence":5,"self_aware":5,"stubborn":5,"trickster_vanara":5,"augmented_spell_poisons":5,"water_lurker":5,"resilient_construction":5,"fierce_flanker":5,"blood_of_dragons":5,"draconic_lineage":5}